TensorToolbox/__init__.py
TensorToolbox/_version.py
TensorToolbox/core/QuanticsTensorTrainMat.py
TensorToolbox/core/QuanticsTensorTrainVec.py
TensorToolbox/core/SpectralTensorTrain.py
TensorToolbox/core/TensorTrainMat.py
TensorToolbox/core/TensorTrainVec.py
TensorToolbox/core/WeightedQuanticsTensorTrainVec.py
TensorToolbox/core/WeightedTensorTrainVec.py
TensorToolbox/core/__init__.py
TensorToolbox/core/auxiliary.py
TensorToolbox/core/candecomp.py
TensorToolbox/core/storage.py
TensorToolbox/core/tensor_wrapper.py
TensorToolbox/multilinalg/__init__.py
TensorToolbox/multilinalg/multilinalg.py
TensorToolbox/unittests/TestQTT.py
TensorToolbox/unittests/TestQTTdmrg.py
TensorToolbox/unittests/TestSQTTdmrg_0D.py
TensorToolbox/unittests/TestSTTcross_0D.py
TensorToolbox/unittests/TestSTTcross_2D.py
TensorToolbox/unittests/TestSTTdmrg_0D.py
TensorToolbox/unittests/TestSTTdmrg_2D.py
TensorToolbox/unittests/TestSTTdmrgcross_0D.py
TensorToolbox/unittests/TestTT.py
TensorToolbox/unittests/TestTT_0.py
TensorToolbox/unittests/TestTT_1.py
TensorToolbox/unittests/TestTT_2.py
TensorToolbox/unittests/TestTT_3.py
TensorToolbox/unittests/TestTT_4.py
TensorToolbox/unittests/TestTT_5.py
TensorToolbox/unittests/TestTT_6.py
TensorToolbox/unittests/TestTT_7.py
TensorToolbox/unittests/TestTTcross.py
TensorToolbox/unittests/TestTTdmrg.py
TensorToolbox/unittests/TestTTdmrgcross.py
TensorToolbox/unittests/TestTensorWrapper.py
TensorToolbox/unittests/TestWTT.py
TensorToolbox/unittests/TestWTT_0.py
TensorToolbox/unittests/TestWTT_2.py
TensorToolbox/unittests/TestWTT_4.py
TensorToolbox/unittests/TestWTT_5.py
TensorToolbox/unittests/TestWTT_6.py
TensorToolbox/unittests/TestWTT_7.py
TensorToolbox/unittests/TestWTTdmrg.py
TensorToolbox/unittests/TestWeightedTensorWrapper.py
TensorToolbox/unittests/__init__.py
TensorToolbox/unittests/auxiliary.py
TensorToolbox/unittests/run_unit_tests.py
TensorToolbox-1.0.22.data/scripts/TensorToolboxUpV030
TensorToolbox-1.0.22.dist-info/METADATA
TensorToolbox-1.0.22.dist-info/RECORD
TensorToolbox-1.0.22.dist-info/WHEEL
TensorToolbox-1.0.22.dist-info/top_level.txt
