Metadata-Version: 2.1
Name: TensorToolbox
Version: 1.0.22
Summary: Tools for the decomposition of tensors
Home-page: http://www.limitcycle.it/dabi/
Author: Daniele Bigoni
Author-email: dabi@limitcycle.it
License: COPYING.LESSER
Platform: UNKNOWN
Requires-Dist: scipy
Requires-Dist: SpectralToolbox
Requires-Dist: mpi4py
Requires-Dist: mpi-map
Requires-Dist: h5py
Requires-Dist: UQToolbox
